{
  "meta_title": "Roupas e Acessórios para Bebês e Crianças | Blue Kids Camisaria Infantil",
  "meta_description": "Roupas e Acessórios para Bebês e Crianças | Blue Kids Camisaria Infantil",
  "sections": [
    {
      "type": "banner-slider",
      "autoplay": 3000,
      "slides": [
        {
          "img": "/img/uploads/banner-topo-bluekids.jpeg",
          "link": "https://bluekids.com.br/search?term=safari",
          "alt": "Novidades Blue Kids",
          "start": "",
          "end": ""
        }
      ]
    },
    {
      "type": "responsive-banner",
      "img": "/img/uploads/banner-regua-blue-kids.jpg",
      "mobile_img": "/img/uploads/banner-regua-blue-kids.jpg",
      "link": "https://bluekids.com.br/pages/trocas",
      "alt": "banner regua roupa social infantil"
    },
    {
      "type": "collection-shelf",
      "shuffle": true,
      "collection_id": "5e286a5362887026009bf0fb",
      "sort": "sales"
    },
    {
      "type": "responsive-banner",
      "img": "/img/uploads/02-1-compressed-1-.jpg",
      "mobile_img": "/img/uploads/02-1-compressed.jpg"
    },
    {
      "type": "collection-shelf",
      "shuffle": true,
      "collection_id": "5e31f8c962887026009eaee0",
      "sort": "sales"
    },
    {
      "type": "responsive-banner",
      "img": "/img/uploads/03-compressed.jpg",
      "link": "https://bluekids.com.br/conjunto-com-bermuda",
      "alt": "banner coleção roupa infantil tematica fundo do mar"
    },
    {
      "type": "collection-shelf",
      "shuffle": true,
      "collection_id": "5e31f85162887026009eaedd",
      "sort": "sales"
    },
    {
      "type": "responsive-banner",
      "img": "/img/uploads/05-compressed.jpg",
      "link": "https://bluekids.com.br/colecao-baloes-e-aventura",
      "alt": "coleção roupa festa infantil balonismo"
    },
    {
      "type": "collection-shelf",
      "shuffle": true,
      "collection_id": "5e31fb8f62887026009eaee4",
      "sort": "sales"
    },
    {
      "type": "responsive-banner",
      "img": "/img/uploads/04-compressed.jpg",
      "link": "https://bluekids.com.br/colecao-circo-magico",
      "alt": "coleção roupa infantil festa dinossauros e balões"
    },
    {
      "type": "collection-shelf",
      "shuffle": true,
      "collection_id": "5e31fc1362887026009eaee6",
      "sort": "sales"
    },
    {
      "type": "collection-shelf",
      "shuffle": true,
      "collection_id": "5e31fd1962887026009eaeea",
      "sort": "sales"
    },
    {
      "type": "collection-shelf",
      "shuffle": true,
      "collection_id": "5e31f7ec62887026009eaedb"
    },
    {
      "type": "responsive-banner",
      "img": "/img/uploads/08.png"
    },
    {
      "type": "collection-shelf",
      "shuffle": true,
      "collection_id": "5e705db57e6552461488d8c5",
      "sort": "sales"
    },
    {
      "type": "collection-shelf",
      "shuffle": true,
      "collection_id": "5e286a5362887026009bf0fb",
      "sort": "sales"
    }
  ]
}